pytest_builtin_types.py
pytest_builtin_types-1.2.dist-info/LICENSE
pytest_builtin_types-1.2.dist-info/METADATA
pytest_builtin_types-1.2.dist-info/WHEEL
pytest_builtin_types-1.2.dist-info/entry_points.txt
pytest_builtin_types-1.2.dist-info/top_level.txt
pytest_builtin_types-1.2.dist-info/RECORD
