Metadata-Version: 2.1
Name: pytest-builtin-types
Version: 1.2
Summary: UNKNOWN
Home-page: UNKNOWN
Author: Tyler Bruno
License: UNKNOWN
Platform: UNKNOWN
Classifier: Framework :: Pytest
Requires-Python: >= 3.6.0
License-File: LICENSE
Requires-Dist: pytest
